Metadata-Version: 2.1
Name: vaspwiki
Version: 1.1.1
Summary: The VASP manual
Home-page: https://github.com/yw-fang/vaspwiki
Author: Yue-Wen FANG
Author-email: fyuewen@gmail.com
License: MIT LICENSE
Keywords: python vasp manual
Platform: UNKNOWN
